{"display":{"firstperson_lefthand":{"rotation":[0.0,90.0,-40.0],"scale":[0.7,0.7,0.7],"translation":[1.13,4.5,1.13]},"firstperson_righthand":{"rotation":[0.0,-90.0,40.0],"scale":[0.7,0.7,0.7],"translation":[1.13,4.5,1.13]},"thirdperson_lefthand":{"rotation":[0.0,90.0,-45.0],"scale":[0.8,0.8,0.8],"translation":[0.0,1.0,-2.5]},"thirdperson_righthand":{"rotation":[0.0,-90.0,45.0],"scale":[0.8,0.8,0.8],"translation":[0.0,1.0,-2.5]}},"overrides":[],"parent":"item/generated","textures":{"layer0":"mineminenomi:items/flintlock"}}